rate_keeper/__init__.py
rate_keeper/rate_keeper.py
rate_keeper-0.4.1.dist-info/METADATA
rate_keeper-0.4.1.dist-info/WHEEL
rate_keeper-0.4.1.dist-info/licenses/LICENSE
rate_keeper-0.4.1.dist-info/RECORD
