Metadata-Version: 2.3
Name: rate-keeper
Version: 0.4.1
Summary: Used to limit function call frequency. It ensures your function is called evenly within the limit rather than being called intensively in a short time.
Project-URL: Homepage, https://github.com/ftnfurina/rate-keeper#readme
Project-URL: Source, https://github.com/ftnfurina/rate-keeper
Project-URL: Tracker, https://github.com/ftnfurina/rate-keeper/issues
Author-email: ftnfurina <ftnfurina@gmail.com>
License: MIT
Keywords: api-rate-limiting,api-throttling,rate-limiter
Classifier: Development Status :: 4 - Beta
Classifier: Intended Audience :: Developers
Classifier: License :: OSI Approved :: MIT License
Classifier: Programming Language :: Python :: 3
Classifier: Programming Language :: Python :: 3.8
Classifier: Programming Language :: Python :: 3.9
Classifier: Programming Language :: Python :: 3.10
Classifier: Programming Language :: Python :: 3.11
Classifier: Programming Language :: Python :: 3.12
Classifier: Topic :: Software Development :: Libraries :: Python Modules
Classifier: Topic :: Utilities
Requires-Python: >=3.8
Requires-Dist: requests>=2.32.3
